fireflink_automation_tool/README.md
fireflink_automation_tool/__init__.py
fireflink_automation_tool/logging_config.py
fireflink_automation_tool/utils.py
fireflink_automation_tool/agent/prompts.py
fireflink_automation_tool/agent/service.py
fireflink_automation_tool/agent/tests.py
fireflink_automation_tool/agent/views.py
fireflink_automation_tool/agent/message_manager/service.py
fireflink_automation_tool/agent/message_manager/tests.py
fireflink_automation_tool/agent/message_manager/views.py
fireflink_automation_tool/browser/browser.py
fireflink_automation_tool/browser/context.py
fireflink_automation_tool/browser/views.py
fireflink_automation_tool/browser/tests/screenshot_test.py
fireflink_automation_tool/browser/tests/test_clicks.py
fireflink_automation_tool/controller/service.py
fireflink_automation_tool/controller/views.py
fireflink_automation_tool/controller/registry/service.py
fireflink_automation_tool/controller/registry/views.py
fireflink_automation_tool/dom/__init__.py
fireflink_automation_tool/dom/buildDomTree.js
fireflink_automation_tool/dom/service.py
fireflink_automation_tool/dom/views.py
fireflink_automation_tool/dom/history_tree_processor/service.py
fireflink_automation_tool/dom/history_tree_processor/view.py
fireflink_automation_tool/dom/tests/extraction_test.py
fireflink_automation_tool/dom/tests/process_dom_test.py
fireflink_automation_tool/telemetry/service.py
fireflink_automation_tool/telemetry/views.py
fireflink_automation_tool-0.1.17.dist-info/METADATA
fireflink_automation_tool-0.1.17.dist-info/WHEEL
fireflink_automation_tool-0.1.17.dist-info/licenses/LICENSE
fireflink_automation_tool-0.1.17.dist-info/RECORD
