Metadata-Version: 2.4
Name: fireflink-automation_tool
Version: 0.1.17
Summary: Make websites accessible for AI agents
Author: Diwahar
License-File: LICENSE
Classifier: License :: OSI Approved :: MIT License
Classifier: Operating System :: OS Independent
Classifier: Programming Language :: Python :: 3
Requires-Python: >=3.11
Requires-Dist: beautifulsoup4>=4.12.3
Requires-Dist: httpx==0.27.2
Requires-Dist: langchain-anthropic>=0.3.0
Requires-Dist: langchain-fireworks>=0.2.5
Requires-Dist: langchain-openai>=0.2.10
Requires-Dist: langchain>=0.3.9
Requires-Dist: maincontentextractor>=0.0.4
Requires-Dist: playwright>=1.49.0
Requires-Dist: posthog>=3.7.4
Requires-Dist: pydantic>=2.10.2
Requires-Dist: python-dotenv>=1.0.1
Requires-Dist: requests>=2.32.3
Provides-Extra: dev
Requires-Dist: build>=1.2.2; extra == 'dev'
Requires-Dist: hatch>=1.13.0; extra == 'dev'
Requires-Dist: pytest-asyncio>=0.24.0; extra == 'dev'
Requires-Dist: pytest>=8.3.3; extra == 'dev'
Requires-Dist: tokencost>=0.1.16; extra == 'dev'
